Metadata-Version: 2.4
Name: algorave
Version: 2.1.1
Summary: Fast, flexible, and advanced augmentation library for deep learning, computer vision, and medical imaging. Algorave offers a wide range of transformations for both 2D (images, masks, bboxes, keypoints) and 3D (volumes, volumetric masks, keypoints) data, with optimized performance and seamless integration into ML workflows.
Author-email: Ben Elfner <algorave@belfner.com>
Maintainer-email: Ben Elfner <algorave@belfner.com>
License: MIT License
Project-URL: Homepage, https://github.com/belfner/algorave
Keywords: 2D augmentation,3D augmentation,aerial photography,anomaly detection,artificial intelligence,autonomous driving,bounding boxes,classification,computer vision,computer vision library,data augmentation,data preprocessing,data science,deep learning,deep learning library,depth estimation,face recognition,fast augmentation,image augmentation,image processing,image transformation,images,instance segmentation,keras,keypoint detection,keypoints,machine learning,machine learning tools,masks,med
Classifier: Development Status :: 5 - Production/Stable
Classifier: Intended Audience :: Developers
Classifier: Intended Audience :: Healthcare Industry
Classifier: Intended Audience :: Information Technology
Classifier: Intended Audience :: Science/Research
Classifier: License :: OSI Approved :: MIT License
Classifier: Operating System :: OS Independent
Classifier: Programming Language :: Python
Classifier: Programming Language :: Python :: 3 :: Only
Classifier: Programming Language :: Python :: 3.9
Classifier: Programming Language :: Python :: 3.10
Classifier: Programming Language :: Python :: 3.11
Classifier: Programming Language :: Python :: 3.12
Classifier: Programming Language :: Python :: 3.13
Classifier: Topic :: Scientific/Engineering
Classifier: Topic :: Scientific/Engineering :: Artificial Intelligence
Classifier: Topic :: Scientific/Engineering :: Astronomy
Classifier: Topic :: Scientific/Engineering :: Atmospheric Science
Classifier: Topic :: Scientific/Engineering :: Bio-Informatics
Classifier: Topic :: Scientific/Engineering :: Image Processing
Classifier: Topic :: Scientific/Engineering :: Physics
Classifier: Topic :: Scientific/Engineering :: Visualization
Classifier: Topic :: Software Development :: Libraries
Classifier: Topic :: Software Development :: Libraries :: Python Modules
Classifier: Typing :: Typed
Requires-Python: >=3.9
License-File: LICENSE
Requires-Dist: numpy>=1.24.4
Requires-Dist: scipy>=1.10.0
Requires-Dist: PyYAML
Requires-Dist: typing-extensions>=4.9.0; python_version < "3.10"
Requires-Dist: pydantic>=2.9.2
Requires-Dist: algocore==0.1.0
Requires-Dist: eval-type-backport; python_version < "3.10"
Requires-Dist: opencv-python>=4.9.0.80
Provides-Extra: hub
Requires-Dist: huggingface-hub; extra == "hub"
Provides-Extra: pytorch
Requires-Dist: torch; extra == "pytorch"
Provides-Extra: text
Requires-Dist: pillow; extra == "text"
Dynamic: license-file
Dynamic: requires-dist
